{
    "Time Created": "2025-07-01 20:18:36",
    "Version": "0.2.0",
    "Author": "Ben Hord",
    "Time Updated": "2025-07-01 20:18:36",
    "Star Name": "TOI-5205",
    "Primary Target": 1,
    "RA": 313.77068826983714,
    "DEC": 24.36098423871825,
    "Coordinate Epoch": "J2016.0",
    "pm_RA": 41.677991037623734,
    "pm_DEC": 52.073519863513035,
    "Jmag": 11.925999641418457,
    "Gmag": 14.902837753295898,
    "Bmag": 16.5116024017334,
    "Teff (K)": 3454.66650390625,
    "logg": 4.781000137329102,
    "VDA Setting": "coadd_50",
    "NIRDA Setting": "samp_4_6",
    "StarRoiDetMethod": 0,
    "numPredefinedStarRois": 1,
    "Planet Name": "TOI-5205b",
    "Planet Letter": "b",
    "Period (days)": 1.630757,
    "Period Uncertainty (days)": 1e-06,
    "Transit Duration (hrs)": 1.4,
    "Transit Epoch (BJD_TDB)": 2459443.47179,
    "Transit Epoch Uncertainty (days)": 0.00019,
    "Obs Window (hrs)": 24.0,
    "ROI_coord_epoch": "J2016.0",
    "ROI_coord": [
        []
    ]
}