{
    "Time Created": "2026-01-02 07:27:03",
    "Version": "1.0.0",
    "Author": "Ben Hord",
    "Time Updated": "2026-01-02 07:27:03",
    "Star Name": "G446188900958928640",
    "Primary Target": 0,
    "RA": 48.36499534912382,
    "DEC": 52.8646747531897,
    "Coordinate Epoch": "J2016.0",
    "pm_RA": 0.9318245747033874,
    "pm_DEC": -3.3262173609902344,
    "Jmag": 12.032,
    "Gmag": 13.461383819580078,
    "Bmag": 13.92128849029541,
    "Teff (K)": 4500.0,
    "logg": NaN,
    "VDA Setting": "coadd_50",
    "NIRDA Setting": "samp_4_6",
    "StarRoiDetMethod": 2,
    "numPredefinedStarRois": 0,
    "Program": "ApStarSurvey"
}