{
    "Time Created": "2024-10-18 01:25:04",
    "Version": "0.1.2",
    "Author": "Ben Hord",
    "Star Name": "DR3_6576226122866434688",
    "RA": 321.6216763616507,
    "DEC": -44.59782025409787,
    "coord_epoch": "J2016.0",
    "pm_RA": 24.29734622190506,
    "pm_DEC": -2.220751396538032,
    "Jmag": 8.564000129699707,
    "Gmag": 9.19289779663086,
    "Teff (K)": 6838.8466796875,
    "logg": 4.017899990081787,
    "VDA Setting": "coadd_50",
    "NIRDA Setting": "samp_4_6",
    "Time Updated": "2024-12-06 22:33:17",
    "StarRoiDetMethod": 1
}