{
    "Time Created": "2024-10-17 04:24:44",
    "Version": "0.2.0",
    "Author": "Ben Hord",
    "Time Updated": "2025-05-16 03:27:43",
    "Star Name": "DR3_3410583403191715328",
    "Primary Target": 0,
    "RA": 69.17762010123691,
    "DEC": 19.49264712100809,
    "Coordinate Epoch": "J2016.0",
    "pm_RA": 31.395507260797334,
    "pm_DEC": -36.39337645472904,
    "Jmag": 7.086999893188477,
    "Gmag": 8.791568756103516,
    "Bmag": 8.94941234588623,
    "Teff (K)": 5517.9638671875,
    "logg": 4.320799827575684,
    "VDA Setting": "coadd_50",
    "NIRDA Setting": "samp_4_4",
    "StarRoiDetMethod": 1,
    "numPredefinedStarRois": 0
}