{
    "Time Created": "2024-10-17 20:05:10",
    "Version": "0.1.2",
    "Author": "Ben Hord",
    "Star Name": "DR3_4147694585408492544",
    "RA": 272.69815057263264,
    "DEC": -12.99120690399614,
    "coord_epoch": "J2016.0",
    "pm_RA": -26.541836913403053,
    "pm_DEC": 6.853758567498195,
    "Jmag": 6.604000091552734,
    "Gmag": 9.025239944458008,
    "Teff (K)": 5114.10107421875,
    "logg": 2.678100109100342,
    "VDA Setting": "coadd_50",
    "NIRDA Setting": "samp_4_3",
    "Time Updated": "2024-12-06 22:33:17",
    "StarRoiDetMethod": 1
}