{
    "Time Created": "2024-10-18 00:56:17",
    "Version": "0.2.0",
    "Author": "Ben Hord",
    "Time Updated": "2025-05-16 03:27:35",
    "Star Name": "DR3_5380367898921640832",
    "Primary Target": 0,
    "RA": 179.4759982969317,
    "DEC": -41.57171686657885,
    "Coordinate Epoch": "J2016.0",
    "pm_RA": 12.927595142389695,
    "pm_DEC": -26.905988653867524,
    "Jmag": 8.175000190734863,
    "Gmag": 9.013992309570312,
    "Bmag": 9.250591278076172,
    "Teff (K)": 6977.5126953125,
    "logg": 3.821899890899658,
    "VDA Setting": "coadd_50",
    "NIRDA Setting": "samp_4_6",
    "StarRoiDetMethod": 1,
    "numPredefinedStarRois": 0
}