{
    "Time Created": "2024-10-17 02:53:26",
    "Version": "0.1.2",
    "Author": "Ben Hord",
    "Star Name": "DR3_1863615107510180480",
    "RA": 308.57324227888097,
    "DEC": 32.90842079542241,
    "coord_epoch": "J2016.0",
    "pm_RA": 16.275602974252166,
    "pm_DEC": 10.19812518502192,
    "Jmag": 8.184000015258789,
    "Gmag": 9.029422760009766,
    "Teff (K)": 6531.05908203125,
    "logg": 3.510499954223633,
    "VDA Setting": "coadd_50",
    "NIRDA Setting": "samp_4_6",
    "Time Updated": "2024-12-06 23:28:50",
    "StarRoiDetMethod": 1
}