{
    "Time Created": "2024-10-17 00:47:50",
    "Version": "0.1.2",
    "Author": "Ben Hord",
    "Star Name": "DR3_391072822597326464",
    "RA": 6.661864858751131,
    "DEC": 48.43333958107274,
    "coord_epoch": "J2016.0",
    "pm_RA": -4.049152825290806,
    "pm_DEC": -7.704607644967495,
    "Jmag": 7.576000213623047,
    "Gmag": 9.2107572555542,
    "Teff (K)": 5113.216796875,
    "logg": 2.813999891281128,
    "VDA Setting": "coadd_50",
    "NIRDA Setting": "samp_4_6",
    "Time Updated": "2024-12-06 22:33:17",
    "StarRoiDetMethod": 1
}