{
    "Time Created": "2026-01-02 18:21:10",
    "Version": "1.0.0",
    "Author": "Ben Hord",
    "Time Updated": "2026-01-02 18:21:10",
    "Star Name": "G206042779630195584",
    "Primary Target": 0,
    "RA": 72.78797393209787,
    "DEC": 43.599107813057174,
    "Coordinate Epoch": "J2016.0",
    "pm_RA": 1.5284804905149492,
    "pm_DEC": -2.432479575933934,
    "Jmag": 11.0,
    "Gmag": 11.407129287719727,
    "Bmag": 11.645381927490234,
    "Teff (K)": 13358.793,
    "logg": 4.1649,
    "VDA Setting": "coadd_50",
    "NIRDA Setting": "samp_4_6",
    "StarRoiDetMethod": 2,
    "numPredefinedStarRois": 0,
    "Program": "ApStarSurvey"
}