{
    "Time Created": "2024-10-17 23:33:01",
    "Version": "0.2.2",
    "Author": "Ben Hord",
    "Time Updated": "2025-10-02 21:23:14",
    "Star Name": "G2903657896534140160",
    "Primary Target": 0,
    "RA": 88.1157050043419,
    "DEC": -29.11473584940655,
    "Coordinate Epoch": "J2016.0",
    "pm_RA": -9.002413582046469,
    "pm_DEC": 6.606160162248118,
    "Jmag": 8.20300006866455,
    "Gmag": 9.065677642822266,
    "Bmag": 9.308043479919434,
    "Teff (K)": 6365.66796875,
    "logg": 3.9086999893188477,
    "VDA Setting": "coadd_50",
    "NIRDA Setting": "samp_4_6",
    "StarRoiDetMethod": 2,
    "numPredefinedStarRois": 0
}