{
    "Time Created": "2024-10-17 20:03:33",
    "Version": "0.2.1",
    "Author": "Ben Hord",
    "Time Updated": "2025-08-14 17:52:34",
    "Star Name": "G2985486987846521088",
    "Primary Target": 0,
    "RA": 82.04086741508247,
    "DEC": -13.567285382737541,
    "Coordinate Epoch": "J2016.0",
    "pm_RA": 16.115379626658314,
    "pm_DEC": -9.661612601878685,
    "Jmag": 7.5879998207092285,
    "Gmag": 9.090826034545898,
    "Bmag": 9.604976654052734,
    "Teff (K)": 5136.73193359375,
    "logg": 3.175800085067749,
    "VDA Setting": "coadd_50",
    "NIRDA Setting": "samp_4_6",
    "StarRoiDetMethod": 1,
    "numPredefinedStarRois": 0
}