{
    "Time Created": "2024-10-17 18:31:13",
    "Version": "0.2.1",
    "Author": "Ben Hord",
    "Time Updated": "2025-08-28 16:02:00",
    "Star Name": "G3007232750864494208",
    "Primary Target": 0,
    "RA": 96.48633149701578,
    "DEC": -6.548227086274033,
    "Coordinate Epoch": "J2016.0",
    "pm_RA": 1.9643110648592867,
    "pm_DEC": -5.613377298426031,
    "Jmag": 7.624000072479248,
    "Gmag": 9.088032722473145,
    "Bmag": 9.576476097106934,
    "Teff (K)": 5152.0986328125,
    "logg": 3.0416998863220215,
    "VDA Setting": "coadd_50",
    "NIRDA Setting": "samp_4_6",
    "StarRoiDetMethod": 1,
    "numPredefinedStarRois": 0
}