{
    "Time Created": "2024-10-16 22:32:58",
    "Version": "0.2.2",
    "Author": "Ben Hord",
    "Time Updated": "2025-10-02 21:23:15",
    "Star Name": "G498435631923016448",
    "Primary Target": 0,
    "RA": 87.46397779348975,
    "DEC": 72.36725999715581,
    "Coordinate Epoch": "J2016.0",
    "pm_RA": -12.178081164073001,
    "pm_DEC": 56.61279206220326,
    "Jmag": 8.133000373840332,
    "Gmag": 9.067427635192871,
    "Bmag": 9.325130462646484,
    "Teff (K)": 6079.19580078125,
    "logg": 4.008600234985352,
    "VDA Setting": "coadd_50",
    "NIRDA Setting": "samp_4_6",
    "StarRoiDetMethod": 2,
    "numPredefinedStarRois": 0
}