{
    "Time Created": "2024-10-17 02:28:31",
    "Version": "0.2.1",
    "Author": "Ben Hord",
    "Time Updated": "2025-08-28 16:01:59",
    "Star Name": "G893998202872932992",
    "Primary Target": 0,
    "RA": 115.38322047876794,
    "DEC": 33.40942333983063,
    "Coordinate Epoch": "J2016.0",
    "pm_RA": -14.244544949157675,
    "pm_DEC": -49.89018822823631,
    "Jmag": 7.991000175476074,
    "Gmag": 9.035018920898438,
    "Bmag": 9.284154891967773,
    "Teff (K)": 6139.29638671875,
    "logg": 4.1894001960754395,
    "VDA Setting": "coadd_50",
    "NIRDA Setting": "samp_4_6",
    "StarRoiDetMethod": 1,
    "numPredefinedStarRois": 0
}