{
    "Time Created": "2024-10-16 23:31:52",
    "Version": "0.2.1",
    "Author": "Ben Hord",
    "Time Updated": "2025-08-15 20:19:22",
    "Star Name": "O1083490098387815424",
    "Primary Target": 0,
    "RA": 120.21775807061907,
    "DEC": 58.87675512464574,
    "Coordinate Epoch": "J2016.0",
    "pm_RA": 20.764654124386404,
    "pm_DEC": -56.34186127296487,
    "Jmag": 7.521999835968018,
    "Gmag": 9.109502792358398,
    "Bmag": 9.644964218139648,
    "Teff (K)": 5135.79296875,
    "logg": 2.791800022125244,
    "VDA Setting": "coadd_50",
    "NIRDA Setting": "samp_4_6",
    "StarRoiDetMethod": 1,
    "numPredefinedStarRois": 0
}