{
    "Time Created": "2024-10-17 02:13:21",
    "Version": "0.2.1",
    "Author": "Ben Hord",
    "Time Updated": "2025-08-15 20:19:23",
    "Star Name": "O1293429061889466624",
    "Primary Target": 0,
    "RA": 223.46637399900538,
    "DEC": 35.79449906532404,
    "Coordinate Epoch": "J2016.0",
    "pm_RA": -13.710496916817434,
    "pm_DEC": -41.098841371079615,
    "Jmag": 8.057999610900879,
    "Gmag": 9.072437286376953,
    "Bmag": 9.381311416625977,
    "Teff (K)": 5931.81884765625,
    "logg": 4.075200080871582,
    "VDA Setting": "coadd_50",
    "NIRDA Setting": "samp_4_6",
    "StarRoiDetMethod": 1,
    "numPredefinedStarRois": 0
}