{
    "Time Created": "2024-10-16 23:29:55",
    "Version": "0.2.1",
    "Author": "Ben Hord",
    "Time Updated": "2025-08-15 20:19:23",
    "Star Name": "O2239490647870962688",
    "Primary Target": 0,
    "RA": 290.36691923263714,
    "DEC": 59.50567582375759,
    "Coordinate Epoch": "J2016.0",
    "pm_RA": -25.982436764268506,
    "pm_DEC": 3.601104111728619,
    "Jmag": 8.26099967956543,
    "Gmag": 9.035083770751953,
    "Bmag": 9.267016410827637,
    "Teff (K)": 6346.71337890625,
    "logg": 4.059500217437744,
    "VDA Setting": "coadd_50",
    "NIRDA Setting": "samp_4_6",
    "StarRoiDetMethod": 1,
    "numPredefinedStarRois": 0
}