{
    "Time Created": "2024-10-17 14:50:00",
    "Version": "0.2.1",
    "Author": "Ben Hord",
    "Time Updated": "2025-08-15 20:19:21",
    "Star Name": "O3741063613151551488",
    "Primary Target": 0,
    "RA": 207.5241706909601,
    "DEC": 14.806272465230045,
    "Coordinate Epoch": "J2016.0",
    "pm_RA": -10.826229769656258,
    "pm_DEC": 18.74181059866937,
    "Jmag": 8.40999984741211,
    "Gmag": 9.168011665344238,
    "Bmag": 9.364964485168457,
    "Teff (K)": 6658.56591796875,
    "logg": 4.000800132751465,
    "VDA Setting": "coadd_50",
    "NIRDA Setting": "samp_4_6",
    "StarRoiDetMethod": 1,
    "numPredefinedStarRois": 0
}