{
    "Time Created": "2024-10-17 17:48:50",
    "Version": "0.1.1",
    "Author": "Ben Hord",
    "Star Name": "Gaia DR3 3125587274856795648",
    "RA": 100.67027718917866,
    "DEC": 0.5017557976347269,
    "coord_epoch": "J2016.0",
    "pm_RA": 6.842664167911512,
    "pm_DEC": -12.727109941082054,
    "Jmag": 8.364999771118164,
    "Gmag": 9.016279220581055,
    "Teff (K)": 6817.08349609375,
    "logg": 4.065000057220459,
    "VDA Setting": "coadd_50",
    "NIRDA Setting": "samp_4_6",
    "Time Updated": "2024-12-04 20:30:56",
    "StarRoiDetMethod": 1,
    "Alt Name": "POT0315"
}