{
    "Time Created": "2024-10-16 22:30:13",
    "Version": "0.1.1",
    "Author": "Ben Hord",
    "Star Name": "Gaia DR3 1713065543009680000",
    "RA": 207.35057219389094,
    "DEC": 75.54074545474224,
    "coord_epoch": "J2016.0",
    "pm_RA": 16.697628872535518,
    "pm_DEC": -2.407997326999999,
    "Jmag": 8.194000244140625,
    "Gmag": 9.03303337097168,
    "Teff (K)": 6199.03466796875,
    "logg": 4.27209997177124,
    "VDA Setting": "coadd_50",
    "NIRDA Setting": "samp_4_6",
    "Time Updated": "2024-12-04 20:30:56",
    "StarRoiDetMethod": 1,
    "Alt Name": "POT0542"
}