{
    "Time Created": "2024-10-18 18:01:20",
    "Version": "0.1.2",
    "Author": "Ben Hord",
    "Planet Name": "WASP-69b",
    "Star Name": "WASP-69",
    "Number of Transits to Capture": 10,
    "RA": 315.0259708078886,
    "DEC": -5.094870064224303,
    "coord_epoch": "J2016.0",
    "pm_RA": 33.777785646192,
    "pm_DEC": -93.58071988791666,
    "Jmag": 8.031999588012695,
    "Gmag": 9.491503715515137,
    "Teff (K)": 4729.37744140625,
    "logg": 4.505799770355225,
    "Planet Letter": "b",
    "Period (days)": 3.86814,
    "Period Uncertainty (days)": 2e-06,
    "Transit Duration (hrs)": 2.1610195,
    "Transit Epoch (BJD_TDB)": 2459798.775459,
    "Transit Epoch Uncertainty (days)": 0.000132,
    "VDA Setting": "coadd_50",
    "NIRDA Setting": "samp_4_6",
    "Time Updated": "2024-12-06 23:28:52",
    "StarRoiDetMethod": 1
}